invisibleroads_macros_database/__init__.py
invisibleroads_macros_database-1.0.2.dist-info/METADATA
invisibleroads_macros_database-1.0.2.dist-info/WHEEL
invisibleroads_macros_database-1.0.2.dist-info/entry_points.txt
invisibleroads_macros_database-1.0.2.dist-info/top_level.txt
invisibleroads_macros_database-1.0.2.dist-info/RECORD
