Metadata-Version: 2.1
Name: invisibleroads-macros-database
Version: 1.0.2
Summary: Shortcut functions for database operations
Home-page: https://github.com/invisibleroads/invisibleroads-macros-database
Author: Roy Hyunjin Han
Author-email: rhh@crosscompute.com
License: UNKNOWN
Keywords: invisibleroads
Platform: UNKNOWN
Classifier: Programming Language :: Python
Classifier: License :: OSI Approved :: MIT License
Requires-Dist: sqlalchemy
Provides-Extra: spatialite
Requires-Dist: shapely ; extra == 'spatialite'
Provides-Extra: test
Requires-Dist: pytest ; extra == 'test'
Requires-Dist: pytest-cov ; extra == 'test'
